tscanapi/TSCAN.py
tscanapi/TSCommon.py
tscanapi/TSDB.py
tscanapi/TSDirver.py
tscanapi/TSEnumdefine.py
tscanapi/TSMasterDevice.py
tscanapi/TSPrase_Fibex.py
tscanapi/TSStructure.py
tscanapi/TSUDS.py
tscanapi/__init__.py
tscanapi/bus.py
tscanapi/config.py
tscanapi/dbc.py
tscanapi/windows/x64/libTSCAN.dll
tscanapi/windows/x64/libTSH.dll
python_can_libtosun-0.1.0.dist-info/METADATA
python_can_libtosun-0.1.0.dist-info/WHEEL
python_can_libtosun-0.1.0.dist-info/entry_points.txt
python_can_libtosun-0.1.0.dist-info/pbr.json
python_can_libtosun-0.1.0.dist-info/top_level.txt
python_can_libtosun-0.1.0.dist-info/RECORD
