Metadata-Version: 2.1
Name: python-can-libtosun
Version: 0.1.0
Summary: 同星libtocan的python-can扩展, only supports Windows x64
Author: notmmao, TOSUN-Shanghai
Author-email: notmmao@gmail.com
Platform: win32
Platform: win-amd64
Classifier: Intended Audience :: Developers
Classifier: Operating System :: Microsoft :: Windows
Classifier: Programming Language :: Python :: 3
Requires-Python: >=3.7
